{"title":"Sexe And Internet.DVDRip.XxX","uid":10355326,"size":2815901170,"categoryP":"porn","categoryS":"movies","magnet":"?xt=urn:btih:02d79e8d0e64071466334a1e5cc07b19e84075db&amp;dn=Sexe+And+Internet.DVDRip.XxX&amp;tr=udp%3A%2F%2Ftracker.openbittorrent.com%3A80&amp;tr=udp%3A%2F%2Fopen.demonii.com%3A1337&amp;tr=udp%3A%2F%2Ftracker.coppersurfer.tk%3A6969&amp;tr=udp%3A%2F%2Fexodus.desync.com%3A6969","seeders":0,"leechers":1,"uploader":"handsome_hulk1253","files":1,"time":1402719212,"description":"Screenshots\n &lt;a href=&quot;\nhttp://adultxpictures.com/xxx/yP5&quot; rel=&quot;nofollow&quot; target=&quot;_NEW&quot;&gt;\nhttp://adultxpictures.com/xxx/yP5&lt;/a&gt; &lt;a href=&quot;\nhttp://adultxpictures.com/xxx/yPV&quot; rel=&quot;nofollow&quot; target=&quot;_NEW&quot;&gt;\nhttp://adultxpictures.com/xxx/yPV&lt;/a&gt;","torrent":{"xt":"urn:btih:02d79e8d0e64071466334a1e5cc07b19e84075db","amp;dn":"Sexe+And+Internet.DVDRip.XxX","amp;tr":["udp%3A%2F%2Ftracker.openbittorrent.com%3A80","udp%3A%2F%2Fopen.demonii.com%3A1337","udp%3A%2F%2Ftracker.coppersurfer.tk%3A6969","udp%3A%2F%2Fexodus.desync.com%3A6969"],"infoHash":"02d79e8d0e64071466334a1e5cc07b19e84075db","infoHashBuffer":{"type":"Buffer","data":[2,215,158,141,14,100,7,20,102,51,74,30,92,192,123,25,232,64,117,219]},"announce":[],"urlList":[]}}