{"title":"[MyFriendsHotMom] India Summer (18139 / 06.12.2014)","uid":10342339,"size":2482134074,"categoryP":"porn","categoryS":"hd___movies","magnet":"?xt=urn:btih:06115364d683d7a140119f55287bc6b940a4505e&amp;dn=%5BMyFriendsHotMom%5D+India+Summer+%2818139+%2F+06.12.2014%29&amp;tr=udp%3A%2F%2Ftracker.openbittorrent.com%3A80&amp;tr=udp%3A%2F%2Fopen.demonii.com%3A1337&amp;tr=udp%3A%2F%2Ftracker.coppersurfer.tk%3A6969&amp;tr=udp%3A%2F%2Fexodus.desync.com%3A6969","seeders":0,"leechers":1,"uploader":"chkm8te","files":1,"time":1402562063,"description":"[MyFriendsHotMom] India Summer (18139 / 06.12.2014)\nres:1080p\n\nDanny stops by his friend's house to see if he got home safe last night. His friend isn't home, but his friend's mom, India, is and she's been curious about her son's whereabouts. Danny tells India about the shenanigans he and her son got into, that's when India realizes she has a missed call on her cell phone. She plays the voice mail and it's her son with a collect call from jail! Danny tries to calm India with a massage, but she needs more than a massage to calm her, she needs Danny's rock hard cock inside her.\n\nScreens: &lt;a href=&quot;\nhttp://xxxhost.me/viewer.php?file=69awrd2797jte2dpkum0.jpg&quot; rel=&quot;nofollow&quot; target=&quot;_NEW&quot;&gt;\nhttp://xxxhost.me/viewer.php?file=69awrd2797jte2dpkum0.jpg&lt;/a&gt;\n &lt;a href=&quot;\nhttp://xxxhost.me/viewer.php?file=up835l88zgfrbchs0ypz.jpg&quot; rel=&quot;nofollow&quot; target=&quot;_NEW&quot;&gt;\nhttp://xxxhost.me/viewer.php?file=up835l88zgfrbchs0ypz.jpg&lt;/a&gt;","torrent":{"xt":"urn:btih:06115364d683d7a140119f55287bc6b940a4505e","amp;dn":"%5BMyFriendsHotMom%5D+India+Summer+%2818139+%2F+06.12.2014%29","amp;tr":["udp%3A%2F%2Ftracker.openbittorrent.com%3A80","udp%3A%2F%2Fopen.demonii.com%3A1337","udp%3A%2F%2Ftracker.coppersurfer.tk%3A6969","udp%3A%2F%2Fexodus.desync.com%3A6969"],"infoHash":"06115364d683d7a140119f55287bc6b940a4505e","infoHashBuffer":{"type":"Buffer","data":[6,17,83,100,214,131,215,161,64,17,159,85,40,123,198,185,64,164,80,94]},"announce":[],"urlList":[]}}