{"title":"BackRoomFacials - Aubrey Addams ( Amateur Blonde Fucked Hardcore","uid":9377643,"size":413647542,"categoryP":"porn","categoryS":"movie_clips","magnet":"?xt=urn:btih:237674479674ab8862d182d61041840b8fb259f7&amp;dn=BackRoomFacials+-+Aubrey+Addams+%28+Amateur+Blonde+Fucked+Hardcore&amp;tr=udp%3A%2F%2Ftracker.openbittorrent.com%3A80&amp;tr=udp%3A%2F%2Fopen.demonii.com%3A1337&amp;tr=udp%3A%2F%2Ftracker.coppersurfer.tk%3A6969&amp;tr=udp%3A%2F%2Fexodus.desync.com%3A6969","seeders":0,"leechers":2,"uploader":"codho","files":-1,"time":1387650093,"description":"Aubrey Addams is a sexy blonde that wants to be part of the Porn world. Well Aubrey Addams, you came to the right place. Where else better to start then here at BangBros. We give everyone equal opportunity. Now lets see if she's cut out for this. Come and watch Aubrey Addams suck dick, get fucked and a face full of cum You be the judge. Enjoy.\n\n\nScreenshot :\n &lt;a href=&quot;\nhttp://bayimg.com/baEklaaFn&quot; rel=&quot;nofollow&quot; target=&quot;_NEW&quot;&gt;\nhttp://bayimg.com/baEklaaFn&lt;/a&gt;","torrent":{"xt":"urn:btih:237674479674ab8862d182d61041840b8fb259f7","amp;dn":"BackRoomFacials+-+Aubrey+Addams+%28+Amateur+Blonde+Fucked+Hardcore","amp;tr":["udp%3A%2F%2Ftracker.openbittorrent.com%3A80","udp%3A%2F%2Fopen.demonii.com%3A1337","udp%3A%2F%2Ftracker.coppersurfer.tk%3A6969","udp%3A%2F%2Fexodus.desync.com%3A6969"],"infoHash":"237674479674ab8862d182d61041840b8fb259f7","infoHashBuffer":{"type":"Buffer","data":[35,118,116,71,150,116,171,136,98,209,130,214,16,65,132,11,143,178,89,247]},"announce":[],"urlList":[]}}