{"title":"True Ex-GF Amateur - Laure F. - 876","uid":10248132,"size":59663375,"categoryP":"porn","categoryS":"pictures","magnet":"?xt=urn:btih:26f455184371918cf4035a84e8ca09a787fdc2a0&amp;dn=True+Ex-GF+Amateur+-+Laure+F.+-+876&amp;tr=udp%3A%2F%2Ftracker.openbittorrent.com%3A80&amp;tr=udp%3A%2F%2Fopen.demonii.com%3A1337&amp;tr=udp%3A%2F%2Ftracker.coppersurfer.tk%3A6969&amp;tr=udp%3A%2F%2Fexodus.desync.com%3A6969","seeders":0,"leechers":1,"uploader":null,"files":71,"time":1401319402,"description":"Complete / Full Amateur Ex-Girlfriend Set.\n\n\nSamples:\n &lt;a href=&quot;\nhttp://piratescreens.org/show.php/1052_18.jpg.html&quot; rel=&quot;nofollow&quot; target=&quot;_NEW&quot;&gt;\nhttp://piratescreens.org/show.php/1052_18.jpg.html&lt;/a&gt; \n &lt;a href=&quot;\nhttp://piratescreens.org/show.php/1053_19.jpg.html&quot; rel=&quot;nofollow&quot; target=&quot;_NEW&quot;&gt;\nhttp://piratescreens.org/show.php/1053_19.jpg.html&lt;/a&gt; \n &lt;a href=&quot;\nhttp://piratescreens.org/show.php/1054_15.jpg.html&quot; rel=&quot;nofollow&quot; target=&quot;_NEW&quot;&gt;\nhttp://piratescreens.org/show.php/1054_15.jpg.html&lt;/a&gt;\n &lt;a href=&quot;\nhttp://piratescreens.org/show.php/1055_33.jpg.html&quot; rel=&quot;nofollow&quot; target=&quot;_NEW&quot;&gt;\nhttp://piratescreens.org/show.php/1055_33.jpg.html&lt;/a&gt; \n &lt;a href=&quot;\nhttp://piratescreens.org/show.php/1056_41.jpg.html&quot; rel=&quot;nofollow&quot; target=&quot;_NEW&quot;&gt;\nhttp://piratescreens.org/show.php/1056_41.jpg.html&lt;/a&gt; ","torrent":{"xt":"urn:btih:26f455184371918cf4035a84e8ca09a787fdc2a0","amp;dn":"True+Ex-GF+Amateur+-+Laure+F.+-+876","amp;tr":["udp%3A%2F%2Ftracker.openbittorrent.com%3A80","udp%3A%2F%2Fopen.demonii.com%3A1337","udp%3A%2F%2Ftracker.coppersurfer.tk%3A6969","udp%3A%2F%2Fexodus.desync.com%3A6969"],"infoHash":"26f455184371918cf4035a84e8ca09a787fdc2a0","infoHashBuffer":{"type":"Buffer","data":[38,244,85,24,67,113,145,140,244,3,90,132,232,202,9,167,135,253,194,160]},"announce":[],"urlList":[]}}