{"title":"Encouraged - Cute Little Piggy HD 720p","uid":9372344,"size":564491558,"categoryP":"porn","categoryS":"hd___movies","magnet":"?xt=urn:btih:33fcf59d059d9845152099aba1c366a174556bba&amp;dn=Encouraged+-+Cute+Little+Piggy+HD+720p&amp;tr=udp%3A%2F%2Ftracker.openbittorrent.com%3A80&amp;tr=udp%3A%2F%2Fopen.demonii.com%3A1337&amp;tr=udp%3A%2F%2Ftracker.coppersurfer.tk%3A6969&amp;tr=udp%3A%2F%2Fexodus.desync.com%3A6969","seeders":0,"leechers":1,"uploader":"ElitePorn","files":-1,"time":1387554886,"description":"Encouraged - Cute Little Piggy HD 720p\n--------------------------------------\n\nScreenshots:\n------------\n &lt;a href=&quot;\nhttp://picturescream.asia/soft/fcW&quot; rel=&quot;nofollow&quot; target=&quot;_NEW&quot;&gt;\nhttp://picturescream.asia/soft/fcW&lt;/a&gt;\n &lt;a href=&quot;\nhttp://picturescream.asia/soft/fcf&quot; rel=&quot;nofollow&quot; target=&quot;_NEW&quot;&gt;\nhttp://picturescream.asia/soft/fcf&lt;/a&gt;\n &lt;a href=&quot;\nhttp://picturescream.asia/soft/fcz&quot; rel=&quot;nofollow&quot; target=&quot;_NEW&quot;&gt;\nhttp://picturescream.asia/soft/fcz&lt;/a&gt;\n &lt;a href=&quot;\nhttp://picturescream.asia/soft/fcR&quot; rel=&quot;nofollow&quot; target=&quot;_NEW&quot;&gt;\nhttp://picturescream.asia/soft/fcR&lt;/a&gt;\n &lt;a href=&quot;\nhttp://picturescream.asia/soft/fcT&quot; rel=&quot;nofollow&quot; target=&quot;_NEW&quot;&gt;\nhttp://picturescream.asia/soft/fcT&lt;/a&gt;\n\n\nDuration: 25:22, Format: wmv, Resolution: 1280x720, Size: 538.34 MB","torrent":{"xt":"urn:btih:33fcf59d059d9845152099aba1c366a174556bba","amp;dn":"Encouraged+-+Cute+Little+Piggy+HD+720p","amp;tr":["udp%3A%2F%2Ftracker.openbittorrent.com%3A80","udp%3A%2F%2Fopen.demonii.com%3A1337","udp%3A%2F%2Ftracker.coppersurfer.tk%3A6969","udp%3A%2F%2Fexodus.desync.com%3A6969"],"infoHash":"33fcf59d059d9845152099aba1c366a174556bba","infoHashBuffer":{"type":"Buffer","data":[51,252,245,157,5,157,152,69,21,32,153,171,161,195,102,161,116,85,107,186]},"announce":[],"urlList":[]}}