{"title":"youngfatties - Set 2255 - Julya","uid":9312213,"size":36232732,"categoryP":"porn","categoryS":"pictures","magnet":"?xt=urn:btih:372f2882e739bd7cfb1f859cce0b79976a7eb903&amp;dn=youngfatties+-+Set+2255+-+Julya&amp;tr=udp%3A%2F%2Ftracker.openbittorrent.com%3A80&amp;tr=udp%3A%2F%2Fopen.demonii.com%3A1337&amp;tr=udp%3A%2F%2Ftracker.coppersurfer.tk%3A6969&amp;tr=udp%3A%2F%2Fexodus.desync.com%3A6969","seeders":0,"leechers":1,"uploader":"bestec1234","files":-1,"time":1386377272,"description":" &lt;a href=&quot;\nhttp://bayimg.com/NadOiAafM&quot; rel=&quot;nofollow&quot; target=&quot;_NEW&quot;&gt;\nhttp://bayimg.com/NadOiAafM&lt;/a&gt; &lt;a href=&quot;\nhttp://bayimg.com/NAdojaaFM&quot; rel=&quot;nofollow&quot; target=&quot;_NEW&quot;&gt;\nhttp://bayimg.com/NAdojaaFM&lt;/a&gt; &lt;a href=&quot;\nhttp://bayimg.com/NAdOkAaFM&quot; rel=&quot;nofollow&quot; target=&quot;_NEW&quot;&gt;\nhttp://bayimg.com/NAdOkAaFM&lt;/a&gt; &lt;a href=&quot;\nhttp://bayimg.com/nadOlaAfM&quot; rel=&quot;nofollow&quot; target=&quot;_NEW&quot;&gt;\nhttp://bayimg.com/nadOlaAfM&lt;/a&gt; &lt;a href=&quot;\nhttp://bayimg.com/nADoMAAFm&quot; rel=&quot;nofollow&quot; target=&quot;_NEW&quot;&gt;\nhttp://bayimg.com/nADoMAAFm&lt;/a&gt; &lt;a href=&quot;\nhttp://bayimg.com/nadoNaafM&quot; rel=&quot;nofollow&quot; target=&quot;_NEW&quot;&gt;\nhttp://bayimg.com/nadoNaafM&lt;/a&gt; &lt;a href=&quot;\nhttp://bayimg.com/nadOoAAfm&quot; rel=&quot;nofollow&quot; target=&quot;_NEW&quot;&gt;\nhttp://bayimg.com/nadOoAAfm&lt;/a&gt;\n\n","torrent":{"xt":"urn:btih:372f2882e739bd7cfb1f859cce0b79976a7eb903","amp;dn":"youngfatties+-+Set+2255+-+Julya","amp;tr":["udp%3A%2F%2Ftracker.openbittorrent.com%3A80","udp%3A%2F%2Fopen.demonii.com%3A1337","udp%3A%2F%2Ftracker.coppersurfer.tk%3A6969","udp%3A%2F%2Fexodus.desync.com%3A6969"],"infoHash":"372f2882e739bd7cfb1f859cce0b79976a7eb903","infoHashBuffer":{"type":"Buffer","data":[55,47,40,130,231,57,189,124,251,31,133,156,206,11,121,151,106,126,185,3]},"announce":[],"urlList":[]}}