{"title":"FemJoy.13.12.21.Suzie.Seduction.XXX.IMAGESET-FuGLi","uid":9377702,"size":106195385,"categoryP":"porn","categoryS":"other","magnet":"?xt=urn:btih:3b709e4c13e6b56d4673688c012f9ffa5a05d8a7&amp;dn=FemJoy.13.12.21.Suzie.Seduction.XXX.IMAGESET-FuGLi&amp;tr=udp%3A%2F%2Ftracker.openbittorrent.com%3A80&amp;tr=udp%3A%2F%2Fopen.demonii.com%3A1337&amp;tr=udp%3A%2F%2Ftracker.coppersurfer.tk%3A6969&amp;tr=udp%3A%2F%2Fexodus.desync.com%3A6969","seeders":0,"leechers":1,"uploader":"Drarbg","files":128,"time":1387650420,"description":"FemJoy.com_13.12.21.Suzie.Seduction.XXX.IMAGESET-FuGLi\n","torrent":{"xt":"urn:btih:3b709e4c13e6b56d4673688c012f9ffa5a05d8a7","amp;dn":"FemJoy.13.12.21.Suzie.Seduction.XXX.IMAGESET-FuGLi","amp;tr":["udp%3A%2F%2Ftracker.openbittorrent.com%3A80","udp%3A%2F%2Fopen.demonii.com%3A1337","udp%3A%2F%2Ftracker.coppersurfer.tk%3A6969","udp%3A%2F%2Fexodus.desync.com%3A6969"],"infoHash":"3b709e4c13e6b56d4673688c012f9ffa5a05d8a7","infoHashBuffer":{"type":"Buffer","data":[59,112,158,76,19,230,181,109,70,115,104,140,1,47,159,250,90,5,216,167]},"announce":[],"urlList":[]}}