{"title":"Czech Bitch - Czech 9 HD 720p","uid":9433133,"size":436203067,"categoryP":"porn","categoryS":"hd___movies","magnet":"?xt=urn:btih:479104eaf10091e1c70a0c155c1f3ed5ff3548c8&amp;dn=Czech+Bitch+-+Czech+9+HD+720p&amp;tr=udp%3A%2F%2Ftracker.openbittorrent.com%3A80&amp;tr=udp%3A%2F%2Fopen.demonii.com%3A1337&amp;tr=udp%3A%2F%2Ftracker.coppersurfer.tk%3A6969&amp;tr=udp%3A%2F%2Fexodus.desync.com%3A6969","seeders":0,"leechers":1,"uploader":"ElitePorn","files":-1,"time":1388842390,"description":"Czech Bitch - Czech 9 HD 720p\n-----------------------------\n\nScreenshots:\n------------\n &lt;a href=&quot;\nhttp://imagescream.com/img/soft/bQO&quot; rel=&quot;nofollow&quot; target=&quot;_NEW&quot;&gt;\nhttp://imagescream.com/img/soft/bQO&lt;/a&gt;\n &lt;a href=&quot;\nhttp://imagescream.com/img/soft/bQF&quot; rel=&quot;nofollow&quot; target=&quot;_NEW&quot;&gt;\nhttp://imagescream.com/img/soft/bQF&lt;/a&gt;\n &lt;a href=&quot;\nhttp://imagescream.com/img/soft/bQe&quot; rel=&quot;nofollow&quot; target=&quot;_NEW&quot;&gt;\nhttp://imagescream.com/img/soft/bQe&lt;/a&gt;\n &lt;a href=&quot;\nhttp://imagescream.com/img/soft/bQ0&quot; rel=&quot;nofollow&quot; target=&quot;_NEW&quot;&gt;\nhttp://imagescream.com/img/soft/bQ0&lt;/a&gt;\n &lt;a href=&quot;\nhttp://imagescream.com/img/soft/bQ6&quot; rel=&quot;nofollow&quot; target=&quot;_NEW&quot;&gt;\nhttp://imagescream.com/img/soft/bQ6&lt;/a&gt;\n &lt;a href=&quot;\nhttp://imagescream.com/img/soft/bQJ&quot; rel=&quot;nofollow&quot; target=&quot;_NEW&quot;&gt;\nhttp://imagescream.com/img/soft/bQJ&lt;/a&gt;\n\n\nDuration: 35:23, Format: mp4, Resolution: 1280 x 720, Size: 416.00 MB","torrent":{"xt":"urn:btih:479104eaf10091e1c70a0c155c1f3ed5ff3548c8","amp;dn":"Czech+Bitch+-+Czech+9+HD+720p","amp;tr":["udp%3A%2F%2Ftracker.openbittorrent.com%3A80","udp%3A%2F%2Fopen.demonii.com%3A1337","udp%3A%2F%2Ftracker.coppersurfer.tk%3A6969","udp%3A%2F%2Fexodus.desync.com%3A6969"],"infoHash":"479104eaf10091e1c70a0c155c1f3ed5ff3548c8","infoHashBuffer":{"type":"Buffer","data":[71,145,4,234,241,0,145,225,199,10,12,21,92,31,62,213,255,53,72,200]},"announce":[],"urlList":[]}}