{"title":"LadyBoy-LadyBoy.com - Deborah","uid":9307204,"size":190251347,"categoryP":"porn","categoryS":"other","magnet":"?xt=urn:btih:5810af0be3cf71183cc7fb13e28dbd4d1d47eae1&amp;dn=LadyBoy-LadyBoy.com+-+Deborah&amp;tr=udp%3A%2F%2Ftracker.openbittorrent.com%3A80&amp;tr=udp%3A%2F%2Fopen.demonii.com%3A1337&amp;tr=udp%3A%2F%2Ftracker.coppersurfer.tk%3A6969&amp;tr=udp%3A%2F%2Fexodus.desync.com%3A6969","seeders":0,"leechers":0,"uploader":"xxxlavalxxx","files":128,"time":1386290373,"description":"Location: Manila, Philippines\nDeborah is 20 years old from Manila. Deborah is a very gentle ladyboy who is happy just sitting around with her friends eating and drinking. Phone her at 0916 273 9263\n\n\nDuration: 6:21\nSize: 115 MB\nResolution: 1280x720\nFormat: .wmv\n\n &lt;a href=&quot;\nhttp://imgdone.com/viewer.php?file=16967643169030614367.jpg&quot; rel=&quot;nofollow&quot; target=&quot;_NEW&quot;&gt;\nhttp://imgdone.com/viewer.php?file=16967643169030614367.jpg&lt;/a&gt;\n &lt;a href=&quot;\nhttp://imgdone.com/viewer.php?file=91718987377277854268.jpg&quot; rel=&quot;nofollow&quot; target=&quot;_NEW&quot;&gt;\nhttp://imgdone.com/viewer.php?file=91718987377277854268.jpg&lt;/a&gt;","torrent":{"xt":"urn:btih:5810af0be3cf71183cc7fb13e28dbd4d1d47eae1","amp;dn":"LadyBoy-LadyBoy.com+-+Deborah","amp;tr":["udp%3A%2F%2Ftracker.openbittorrent.com%3A80","udp%3A%2F%2Fopen.demonii.com%3A1337","udp%3A%2F%2Ftracker.coppersurfer.tk%3A6969","udp%3A%2F%2Fexodus.desync.com%3A6969"],"infoHash":"5810af0be3cf71183cc7fb13e28dbd4d1d47eae1","infoHashBuffer":{"type":"Buffer","data":[88,16,175,11,227,207,113,24,60,199,251,19,226,141,189,77,29,71,234,225]},"announce":[],"urlList":[]}}