{"title":"ImmoralLive.14.05.28.Laela.Pryce.And.Savannah.Fox.XXX.1080p.MP4-","uid":10243444,"size":2234077944,"categoryP":"porn","categoryS":"other","magnet":"?xt=urn:btih:58903f06031dea61172d9a904cf18d4c8b010ad2&amp;dn=ImmoralLive.14.05.28.Laela.Pryce.And.Savannah.Fox.XXX.1080p.MP4-&amp;tr=udp%3A%2F%2Ftracker.openbittorrent.com%3A80&amp;tr=udp%3A%2F%2Fopen.demonii.com%3A1337&amp;tr=udp%3A%2F%2Ftracker.coppersurfer.tk%3A6969&amp;tr=udp%3A%2F%2Fexodus.desync.com%3A6969","seeders":0,"leechers":0,"uploader":"Drarbg","files":3,"time":1401259565,"description":"ImmoralLive.14.05.28.Laela.Pryce.And.Savannah.Fox.XXX.1080p.MP4-KTR\n-----------------------------------------\nScreens : &lt;a href=&quot;\nhttp://imagecurl.org/viewer.php?file=77394888884222431003.jpg&quot; rel=&quot;nofollow&quot; target=&quot;_NEW&quot;&gt;\nhttp://imagecurl.org/viewer.php?file=77394888884222431003.jpg&lt;/a&gt;\n\n","torrent":{"xt":"urn:btih:58903f06031dea61172d9a904cf18d4c8b010ad2","amp;dn":"ImmoralLive.14.05.28.Laela.Pryce.And.Savannah.Fox.XXX.1080p.MP4-","amp;tr":["udp%3A%2F%2Ftracker.openbittorrent.com%3A80","udp%3A%2F%2Fopen.demonii.com%3A1337","udp%3A%2F%2Ftracker.coppersurfer.tk%3A6969","udp%3A%2F%2Fexodus.desync.com%3A6969"],"infoHash":"58903f06031dea61172d9a904cf18d4c8b010ad2","infoHashBuffer":{"type":"Buffer","data":[88,144,63,6,3,29,234,97,23,45,154,144,76,241,141,76,139,1,10,210]},"announce":[],"urlList":[]}}