{"title":"KarupsPC.13.12.06.Connie.Smith.Solo.1.XXX.720p.MP4-KTR","uid":9309395,"size":840771635,"categoryP":"porn","categoryS":"other","magnet":"?xt=urn:btih:5b34485758a895144416d7a1436e7eff01f1f6d3&amp;dn=KarupsPC.13.12.06.Connie.Smith.Solo.1.XXX.720p.MP4-KTR&amp;tr=udp%3A%2F%2Ftracker.openbittorrent.com%3A80&amp;tr=udp%3A%2F%2Fopen.demonii.com%3A1337&amp;tr=udp%3A%2F%2Ftracker.coppersurfer.tk%3A6969&amp;tr=udp%3A%2F%2Fexodus.desync.com%3A6969","seeders":0,"leechers":0,"uploader":"Drarbg","files":3,"time":1386379738,"description":"KarupsPC.13.12.06.Connie.Smith.Solo.1.XXX.720p.MP4-KTR\n-----------------------------------------\nScreens : &lt;a href=&quot;\nhttp://imagecurl.org/viewer.php?file=68503398736576721360.jpg&quot; rel=&quot;nofollow&quot; target=&quot;_NEW&quot;&gt;\nhttp://imagecurl.org/viewer.php?file=68503398736576721360.jpg&lt;/a&gt;\n\n","torrent":{"xt":"urn:btih:5b34485758a895144416d7a1436e7eff01f1f6d3","amp;dn":"KarupsPC.13.12.06.Connie.Smith.Solo.1.XXX.720p.MP4-KTR","amp;tr":["udp%3A%2F%2Ftracker.openbittorrent.com%3A80","udp%3A%2F%2Fopen.demonii.com%3A1337","udp%3A%2F%2Ftracker.coppersurfer.tk%3A6969","udp%3A%2F%2Fexodus.desync.com%3A6969"],"infoHash":"5b34485758a895144416d7a1436e7eff01f1f6d3","infoHashBuffer":{"type":"Buffer","data":[91,52,72,87,88,168,149,20,68,22,215,161,67,110,126,255,1,241,246,211]},"announce":[],"urlList":[]}}