{"title":"[UTW-Vivid]_Suisei_no_Gargantia_-_14_[BD][h264-1080p_FLAC][52BCE","uid":9351140,"size":2336336939,"categoryP":"video","categoryS":"hd___tv_shows","magnet":"?xt=urn:btih:74518cc02c142265b444c5d23fec3271abd50aaa&amp;dn=%5BUTW-Vivid%5D_Suisei_no_Gargantia_-_14_%5BBD%5D%5Bh264-1080p_FLAC%5D%5B52BCE&amp;tr=udp%3A%2F%2Ftracker.openbittorrent.com%3A80&amp;tr=udp%3A%2F%2Fopen.demonii.com%3A1337&amp;tr=udp%3A%2F%2Ftracker.coppersurfer.tk%3A6969&amp;tr=udp%3A%2F%2Fexodus.desync.com%3A6969","seeders":0,"leechers":0,"uploader":"darkj6","files":1,"time":1387124540,"description":" ______   _______  ______    ___   _      ___  --------|\n|      | |   _   ||    _ |  |   | | |    |   ||   |----|    \n|  _    ||  |_|  ||   | ||  |   |_| |    |   ||   |___ \n| | |   ||       ||   |_||_ |      _|    |   ||    _  |\n| |_|   ||       ||    __  ||     |_  ___|   ||   | | |\n|       ||   _   ||   |  | ||    _  ||       ||   |_| |\n|______| |__| |__||___|  |_||___| |_||_______||_______|\n\n\nEpisode 14 (OVA 1) of Suisei no Gargantia, brought to you by UTW and Vivid.\n\nThis is a 1080p BD release encoded in 10bit h264 with FLAC audio. If you have any problems with playback or subtitle rendering, please make sure you're using the latest version of the CCCP.","torrent":{"xt":"urn:btih:74518cc02c142265b444c5d23fec3271abd50aaa","amp;dn":"%5BUTW-Vivid%5D_Suisei_no_Gargantia_-_14_%5BBD%5D%5Bh264-1080p_FLAC%5D%5B52BCE","amp;tr":["udp%3A%2F%2Ftracker.openbittorrent.com%3A80","udp%3A%2F%2Fopen.demonii.com%3A1337","udp%3A%2F%2Ftracker.coppersurfer.tk%3A6969","udp%3A%2F%2Fexodus.desync.com%3A6969"],"infoHash":"74518cc02c142265b444c5d23fec3271abd50aaa","infoHashBuffer":{"type":"Buffer","data":[116,81,140,192,44,20,34,101,180,68,197,210,63,236,50,113,171,213,10,170]},"announce":[],"urlList":[]}}