{"title":"Quando Meno Te Lo Aspetti.DVDRip.XxX.avi","uid":10328022,"size":733560832,"categoryP":"porn","categoryS":"movies","magnet":"?xt=urn:btih:7b5629159726a0d72893889a162ca1529fb9ad11&amp;dn=Quando+Meno+Te+Lo+Aspetti.DVDRip.XxX.avi&amp;tr=udp%3A%2F%2Ftracker.openbittorrent.com%3A80&amp;tr=udp%3A%2F%2Fopen.demonii.com%3A1337&amp;tr=udp%3A%2F%2Ftracker.coppersurfer.tk%3A6969&amp;tr=udp%3A%2F%2Fexodus.desync.com%3A6969","seeders":0,"leechers":4,"uploader":"handsome_hulk1253","files":1,"time":1402378391,"description":"Screenshots\n\n\n &lt;a href=&quot;\nhttp://adultxpictures.com/xxx/y9F&quot; rel=&quot;nofollow&quot; target=&quot;_NEW&quot;&gt;\nhttp://adultxpictures.com/xxx/y9F&lt;/a&gt; &lt;a href=&quot;\nhttp://adultxpictures.com/xxx/y9c&quot; rel=&quot;nofollow&quot; target=&quot;_NEW&quot;&gt;\nhttp://adultxpictures.com/xxx/y9c&lt;/a&gt;","torrent":{"xt":"urn:btih:7b5629159726a0d72893889a162ca1529fb9ad11","amp;dn":"Quando+Meno+Te+Lo+Aspetti.DVDRip.XxX.avi","amp;tr":["udp%3A%2F%2Ftracker.openbittorrent.com%3A80","udp%3A%2F%2Fopen.demonii.com%3A1337","udp%3A%2F%2Ftracker.coppersurfer.tk%3A6969","udp%3A%2F%2Fexodus.desync.com%3A6969"],"infoHash":"7b5629159726a0d72893889a162ca1529fb9ad11","infoHashBuffer":{"type":"Buffer","data":[123,86,41,21,151,38,160,215,40,147,136,154,22,44,161,82,159,185,173,17]},"announce":[],"urlList":[]}}