{"title":"Runner Runner 2013 HC 720p WEBRIP x264 AC3 CrEwSaDe","uid":9367422,"size":2877128685,"categoryP":"video","categoryS":"hd___movies","magnet":"?xt=urn:btih:893ded4388f6e43fcda05c35edbe2473ade64607&amp;dn=Runner+Runner+2013+HC+720p+WEBRIP+x264+AC3+CrEwSaDe&amp;tr=udp%3A%2F%2Ftracker.openbittorrent.com%3A80&amp;tr=udp%3A%2F%2Fopen.demonii.com%3A1337&amp;tr=udp%3A%2F%2Ftracker.coppersurfer.tk%3A6969&amp;tr=udp%3A%2F%2Fexodus.desync.com%3A6969","seeders":0,"leechers":0,"uploader":"hotpena","files":-1,"time":1387458230,"description":"PLOT\nWhen a poor college student who cracks an online poker game goes bust, he arranges a face-to-face with the man he thinks cheated him, a sly offshore entrepreneur.\n\n\nACTORS\nBen Affleck, Justin Timberlake, Gemma Arterton\n\n\nRELEASED\n2013\n\n\nIMDB &lt;a href=&quot;\nhttp://www.imdb.com/title/tt2364841/&quot; rel=&quot;nofollow&quot; target=&quot;_NEW&quot;&gt;\nhttp://www.imdb.com/title/tt2364841/&lt;/a&gt;\n\nScreen &lt;a href=&quot;\nhttp://www.imgclik.com/viewer.php?file=78306950669782077855.jpg&quot; rel=&quot;nofollow&quot; target=&quot;_NEW&quot;&gt;\nhttp://www.imgclik.com/viewer.php?file=78306950669782077855.jpg&lt;/a&gt;\n &lt;a href=&quot;\nhttp://www.imgclik.com/viewer.php?file=80877024405292539011.jpg&quot; rel=&quot;nofollow&quot; target=&quot;_NEW&quot;&gt;\nhttp://www.imgclik.com/viewer.php?file=80877024405292539011.jpg&lt;/a&gt;\n &lt;a href=&quot;\nhttp://www.imgclik.com/viewer.php?file=46535781959416333808.jpg&quot; rel=&quot;nofollow&quot; target=&quot;_NEW&quot;&gt;\nhttp://www.imgclik.com/viewer.php?file=46535781959416333808.jpg&lt;/a&gt;\n\nSIZE:\n2848972357 bytes (2.65 GiB),\n\nDURATION:\n01:31:39,\n\nAVG-BITRATE:\n4145 kb/s\n\nAUDIO:\nac3, 48000 Hz, 5:1 (eng)\n\nVIDEO:\nh264, yuv420p, 1280x528, 23.98 fps(r) =&gt; 1270x528","torrent":{"xt":"urn:btih:893ded4388f6e43fcda05c35edbe2473ade64607","amp;dn":"Runner+Runner+2013+HC+720p+WEBRIP+x264+AC3+CrEwSaDe","amp;tr":["udp%3A%2F%2Ftracker.openbittorrent.com%3A80","udp%3A%2F%2Fopen.demonii.com%3A1337","udp%3A%2F%2Ftracker.coppersurfer.tk%3A6969","udp%3A%2F%2Fexodus.desync.com%3A6969"],"infoHash":"893ded4388f6e43fcda05c35edbe2473ade64607","infoHashBuffer":{"type":"Buffer","data":[137,61,237,67,136,246,228,63,205,160,92,53,237,190,36,115,173,230,70,7]},"announce":[],"urlList":[]}}