{"title":"Stolen Vacation Pics - Tammy T. - 006","uid":9281061,"size":68679180,"categoryP":"porn","categoryS":"pictures","magnet":"?xt=urn:btih:8ab3f55ff05b9f39561ed8c7e0d93136c2311321&amp;dn=Stolen+Vacation+Pics+-+Tammy+T.+-+006&amp;tr=udp%3A%2F%2Ftracker.openbittorrent.com%3A80&amp;tr=udp%3A%2F%2Fopen.demonii.com%3A1337&amp;tr=udp%3A%2F%2Ftracker.coppersurfer.tk%3A6969&amp;tr=udp%3A%2F%2Fexodus.desync.com%3A6969","seeders":0,"leechers":2,"uploader":null,"files":92,"time":1385941681,"description":"Complete Set of Stolen Vacation Pics. \n\n\nSamples are SFW, Full Set is NSFW. Mostly topless shots. \n\n\nSFW Samples:\n &lt;a href=&quot;\nhttp://easyimghost.com/ImageHosting/11333_extov0027003.jpg.html&quot; rel=&quot;nofollow&quot; target=&quot;_NEW&quot;&gt;\nhttp://easyimghost.com/ImageHosting/11333_extov0027003.jpg.html&lt;/a&gt; \n &lt;a href=&quot;\nhttp://easyimghost.com/ImageHosting/11334_extov0027008.jpg.html&quot; rel=&quot;nofollow&quot; target=&quot;_NEW&quot;&gt;\nhttp://easyimghost.com/ImageHosting/11334_extov0027008.jpg.html&lt;/a&gt; \n &lt;a href=&quot;\nhttp://easyimghost.com/ImageHosting/11335_extov0027001.jpg.html&quot; rel=&quot;nofollow&quot; target=&quot;_NEW&quot;&gt;\nhttp://easyimghost.com/ImageHosting/11335_extov0027001.jpg.html&lt;/a&gt;\n &lt;a href=&quot;\nhttp://easyimghost.com/ImageHosting/11336_extov0027004.jpg.html&quot; rel=&quot;nofollow&quot; target=&quot;_NEW&quot;&gt;\nhttp://easyimghost.com/ImageHosting/11336_extov0027004.jpg.html&lt;/a&gt; \n &lt;a href=&quot;\nhttp://easyimghost.com/ImageHosting/11337_extov0027033.jpg.html&quot; rel=&quot;nofollow&quot; target=&quot;_NEW&quot;&gt;\nhttp://easyimghost.com/ImageHosting/11337_extov0027033.jpg.html&lt;/a&gt; ","torrent":{"xt":"urn:btih:8ab3f55ff05b9f39561ed8c7e0d93136c2311321","amp;dn":"Stolen+Vacation+Pics+-+Tammy+T.+-+006","amp;tr":["udp%3A%2F%2Ftracker.openbittorrent.com%3A80","udp%3A%2F%2Fopen.demonii.com%3A1337","udp%3A%2F%2Ftracker.coppersurfer.tk%3A6969","udp%3A%2F%2Fexodus.desync.com%3A6969"],"infoHash":"8ab3f55ff05b9f39561ed8c7e0d93136c2311321","infoHashBuffer":{"type":"Buffer","data":[138,179,245,95,240,91,159,57,86,30,216,199,224,217,49,54,194,49,19,33]},"announce":[],"urlList":[]}}