{"title":"Overkill - The Years Of Decay (1989) [2013 Japanese Edition] [EA","uid":9360174,"size":434650907,"categoryP":"audio","categoryS":"flac","magnet":"?xt=urn:btih:9156c3df299ea934da6390012b2eac496e201267&amp;dn=Overkill+-+The+Years+Of+Decay+%281989%29+%5B2013+Japanese+Edition%5D+%5BEA&amp;tr=udp%3A%2F%2Ftracker.openbittorrent.com%3A80&amp;tr=udp%3A%2F%2Fopen.demonii.com%3A1337&amp;tr=udp%3A%2F%2Ftracker.coppersurfer.tk%3A6969&amp;tr=udp%3A%2F%2Fexodus.desync.com%3A6969","seeders":0,"leechers":0,"uploader":"qculfj","files":21,"time":1387298436,"description":"01. Time To Kill (6:17)\n02. Elimination (4:35)\n03. I Hate (3:47)\n04. Nothing To Die For (4:22)\n05. Playing With Spiders/Skullkrusher (10:15)\n06. Birth Of Tension (5:05)\n07. Who Tends The Fire (8:12)\n08. The Years Of Decay (8:00)\n09. E.vil N.ever D.ies (5:51)","torrent":{"xt":"urn:btih:9156c3df299ea934da6390012b2eac496e201267","amp;dn":"Overkill+-+The+Years+Of+Decay+%281989%29+%5B2013+Japanese+Edition%5D+%5BEA","amp;tr":["udp%3A%2F%2Ftracker.openbittorrent.com%3A80","udp%3A%2F%2Fopen.demonii.com%3A1337","udp%3A%2F%2Ftracker.coppersurfer.tk%3A6969","udp%3A%2F%2Fexodus.desync.com%3A6969"],"infoHash":"9156c3df299ea934da6390012b2eac496e201267","infoHashBuffer":{"type":"Buffer","data":[145,86,195,223,41,158,169,52,218,99,144,1,43,46,172,73,110,32,18,103]},"announce":[],"urlList":[]}}