{"title":"Schau wie ich die Teenies ficke 6 [DVDRip]","uid":9333994,"size":735485952,"categoryP":"porn","categoryS":"movies","magnet":"?xt=urn:btih:9de94bed5a843cb75dee0156f5d7ce0c7d976e1d&amp;dn=Schau+wie+ich+die+Teenies+ficke+6+%5BDVDRip%5D&amp;tr=udp%3A%2F%2Ftracker.openbittorrent.com%3A80&amp;tr=udp%3A%2F%2Fopen.demonii.com%3A1337&amp;tr=udp%3A%2F%2Ftracker.coppersurfer.tk%3A6969&amp;tr=udp%3A%2F%2Fexodus.desync.com%3A6969","seeders":0,"leechers":0,"uploader":"chkm8te","files":1,"time":1386821294,"description":"Schau wie ich die Teenies ficke 6 [DVDRip]\n\nKacha, Kim, Meret Melt, Natalia, Zuzie Boobies, Philippe Soine\n\nThese young pussies cannot get enough of some big juicy cock. They are more than willing to get down on their knees and suck you dry. Then they'll bend over for you and open their asses up nice and wide. Whether they're blondes or brunettes, these girls are ready for cum and will do whatever it takes to get it!\n\nScreens: &lt;a href=&quot;\nhttp://xxxhost.me/viewer.php?file=zax1d1o7q6ckc5gxc523.jpg&quot; rel=&quot;nofollow&quot; target=&quot;_NEW&quot;&gt;\nhttp://xxxhost.me/viewer.php?file=zax1d1o7q6ckc5gxc523.jpg&lt;/a&gt;\n &lt;a href=&quot;\nhttp://xxxhost.me/viewer.php?file=kf7jlqss77zjhtivtm2v.jpg&quot; rel=&quot;nofollow&quot; target=&quot;_NEW&quot;&gt;\nhttp://xxxhost.me/viewer.php?file=kf7jlqss77zjhtivtm2v.jpg&lt;/a&gt;","torrent":{"xt":"urn:btih:9de94bed5a843cb75dee0156f5d7ce0c7d976e1d","amp;dn":"Schau+wie+ich+die+Teenies+ficke+6+%5BDVDRip%5D","amp;tr":["udp%3A%2F%2Ftracker.openbittorrent.com%3A80","udp%3A%2F%2Fopen.demonii.com%3A1337","udp%3A%2F%2Ftracker.coppersurfer.tk%3A6969","udp%3A%2F%2Fexodus.desync.com%3A6969"],"infoHash":"9de94bed5a843cb75dee0156f5d7ce0c7d976e1d","infoHashBuffer":{"type":"Buffer","data":[157,233,75,237,90,132,60,183,93,238,1,86,245,215,206,12,125,151,110,29]},"announce":[],"urlList":[]}}