{"title":"she  correctly","uid":9416442,"size":374213851,"categoryP":"porn","categoryS":"movie_clips","magnet":"?xt=urn:btih:b6acac1d73a0780ef19a18d389fe2c30e017bd83&amp;dn=she++correctly&amp;tr=udp%3A%2F%2Ftracker.openbittorrent.com%3A80&amp;tr=udp%3A%2F%2Fopen.demonii.com%3A1337&amp;tr=udp%3A%2F%2Ftracker.coppersurfer.tk%3A6969&amp;tr=udp%3A%2F%2Fexodus.desync.com%3A6969","seeders":0,"leechers":0,"uploader":"RaspotocjeGori","files":1,"time":1388455423,"description":" &lt;a href=&quot;http://fastfap.net/?p=2096&quot; rel=&quot;nofollow&quot; target=&quot;_NEW&quot;&gt;http://fastfap.net/?p=2096&lt;/a&gt;","torrent":{"xt":"urn:btih:b6acac1d73a0780ef19a18d389fe2c30e017bd83","amp;dn":"she++correctly","amp;tr":["udp%3A%2F%2Ftracker.openbittorrent.com%3A80","udp%3A%2F%2Fopen.demonii.com%3A1337","udp%3A%2F%2Ftracker.coppersurfer.tk%3A6969","udp%3A%2F%2Fexodus.desync.com%3A6969"],"infoHash":"b6acac1d73a0780ef19a18d389fe2c30e017bd83","infoHashBuffer":{"type":"Buffer","data":[182,172,172,29,115,160,120,14,241,154,24,211,137,254,44,48,224,23,189,131]},"announce":[],"urlList":[]}}