{"title":"FemJoy.14.06.01.Ella.C.Red.Rouge.XXX.IMAGESET-GAGBALL","uid":10273430,"size":61053947,"categoryP":"porn","categoryS":"other","magnet":"?xt=urn:btih:ba18e8cd54670b7bd6a27d3ec0d6183b1fabf5f1&amp;dn=FemJoy.14.06.01.Ella.C.Red.Rouge.XXX.IMAGESET-GAGBALL&amp;tr=udp%3A%2F%2Ftracker.openbittorrent.com%3A80&amp;tr=udp%3A%2F%2Fopen.demonii.com%3A1337&amp;tr=udp%3A%2F%2Ftracker.coppersurfer.tk%3A6969&amp;tr=udp%3A%2F%2Fexodus.desync.com%3A6969","seeders":0,"leechers":1,"uploader":"Drarbg","files":84,"time":1401581715,"description":"FemJoy.com_14.06.01.Ella.C.Red.Rouge.XXX.IMAGESET-GAGBALL\n","torrent":{"xt":"urn:btih:ba18e8cd54670b7bd6a27d3ec0d6183b1fabf5f1","amp;dn":"FemJoy.14.06.01.Ella.C.Red.Rouge.XXX.IMAGESET-GAGBALL","amp;tr":["udp%3A%2F%2Ftracker.openbittorrent.com%3A80","udp%3A%2F%2Fopen.demonii.com%3A1337","udp%3A%2F%2Ftracker.coppersurfer.tk%3A6969","udp%3A%2F%2Fexodus.desync.com%3A6969"],"infoHash":"ba18e8cd54670b7bd6a27d3ec0d6183b1fabf5f1","infoHashBuffer":{"type":"Buffer","data":[186,24,232,205,84,103,11,123,214,162,125,62,192,214,24,59,31,171,245,241]},"announce":[],"urlList":[]}}