{"title":"Now You See Me (2013) DTS-PAL-DVDR-NLU002","uid":9306321,"size":4690086523,"categoryP":"video","categoryS":"movies_dvdr","magnet":"?xt=urn:btih:beadc22eb02bedfe701aa6aea6aea0f582eca75c&amp;dn=Now+You+See+Me+%282013%29+DTS-PAL-DVDR-NLU002&amp;tr=udp%3A%2F%2Ftracker.openbittorrent.com%3A80&amp;tr=udp%3A%2F%2Fopen.demonii.com%3A1337&amp;tr=udp%3A%2F%2Ftracker.coppersurfer.tk%3A6969&amp;tr=udp%3A%2F%2Fexodus.desync.com%3A6969","seeders":0,"leechers":0,"uploader":"NLUPPER002","files":-1,"time":1386317891,"description":"Now You See Me (2013) DTS-PAL-DVDR-NLU002\n.\n[IMG]http://imageshack.us/a/img36/9852/huer.jpg[/IMG]\n.\nPG-13  -   115 min  -  Crime | Mystery | Thriller  -  31 May 2013 (USA) \nRated PG-13 for language, some action and sexual content\n. &lt;a href=&quot;\nhttp://www.imdb.com/title/tt1670345/&quot; rel=&quot;nofollow&quot; target=&quot;_NEW&quot;&gt;\nhttp://www.imdb.com/title/tt1670345/&lt;/a&gt;\n. &lt;a href=&quot;\nhttp://www.moviemeter.nl/film/82187&quot; rel=&quot;nofollow&quot; target=&quot;_NEW&quot;&gt;\nhttp://www.moviemeter.nl/film/82187&lt;/a&gt;\n.\nPLOT\n.\nAn FBI agent and an Interpol detective track a team of illusionists,\nwho pull off bank heists during their performances and reward their audiences with the money. \n.\nSource: DVD9\nFormat: DVD5\nVideo: PAL, Encoder CCE-10-passes\nAudio: English DD5.1, English DTS\nRetail Subtitles: Dutch, English SDH. \nMenu: Yes\nExtra's: No\nRemoved: All The Crap\nRewrite: Full DVDR Structure\nRewrite: Full Menu Structure Every button is re-writen and checked on working.\nAdded: All Subtitles a Yellow stream.\n.\nEnjoy another fine quality from NLU002\n.\n- DVD-RB v1.28.2\n- AVISYNTH 2.5.8.0\n- CCE 2.70.2.0 encoder selected.\n- Source: NOW_YOU_SEE_ME_DVD9\n- VTS_01: 2.783.633 sectors.\n-- Scanning and writing .D2V &amp; .AVS files\n-- Processed 179.482 frames.\n-- Building .AVS and .ECL files\n- Reduction Level for DVD-5: 75,1%\n- Overall Bitrate : 3.808Kbs\n- Space for Video : 3.337.250KB\n- HIGH/LOW/TYPICAL Bitrates: 4.548/1.005/3.808 Kbs\nPhase I, PREPARATION completed in 1 minutes.\nPhase II ENCODING completed in  220 minutes.\nPhase III, REBUILD completed in 5 minutes.\n.\nDVD-5 full at: 99,78% :)\n.\nDisc media: ISO (DVD-Video)\nDisc region: 1, 2, 3, 4, 5, 6, 7, 8\nVolume name: NOW_YOU_SEE_ME_2013_PAL_DVDR_NLU\nVideo standard: PAL\nLayer 0 size: 2290080 sectors (4472 MBytes)\n\nCSS (Content Scramble System) protection not found.\nRC (Region Code) protection not found.\nRCE (Region Code Enhancement) protection not found.\nAPS (Analog Protection System) protection not found.\nUOPs (User Operation Prohibitions) protection not found.\n\nInvalid PTTs, PGCIs, PGCs, TMAPs, CELLs, VOBUs protection not found!\nFake vts protection not found!\nBad sector protection not found!\nStructure protection (ARccOS, RipGuard, etc.) not found.\nUnplayable cell not found.","torrent":{"xt":"urn:btih:beadc22eb02bedfe701aa6aea6aea0f582eca75c","amp;dn":"Now+You+See+Me+%282013%29+DTS-PAL-DVDR-NLU002","amp;tr":["udp%3A%2F%2Ftracker.openbittorrent.com%3A80","udp%3A%2F%2Fopen.demonii.com%3A1337","udp%3A%2F%2Ftracker.coppersurfer.tk%3A6969","udp%3A%2F%2Fexodus.desync.com%3A6969"],"infoHash":"beadc22eb02bedfe701aa6aea6aea0f582eca75c","infoHashBuffer":{"type":"Buffer","data":[190,173,194,46,176,43,237,254,112,26,166,174,166,174,160,245,130,236,167,92]},"announce":[],"urlList":[]}}