{"title":"[FullyClothedSex] Angel Piaf aka Chaynee (The Cuckold Gets The L","uid":9330973,"size":894667015,"categoryP":"porn","categoryS":"hd___movies","magnet":"?xt=urn:btih:beedd86e08297e43af201a6e648ab4617e81b77a&amp;dn=%5BFullyClothedSex%5D+Angel+Piaf+aka+Chaynee+%28The+Cuckold+Gets+The+L&amp;tr=udp%3A%2F%2Ftracker.openbittorrent.com%3A80&amp;tr=udp%3A%2F%2Fopen.demonii.com%3A1337&amp;tr=udp%3A%2F%2Ftracker.coppersurfer.tk%3A6969&amp;tr=udp%3A%2F%2Fexodus.desync.com%3A6969","seeders":0,"leechers":1,"uploader":"chkm8te","files":1,"time":1386729842,"description":"[FullyClothedSex] Angel Piaf aka Chaynee (The Cuckold Gets The Last Laugh / 12.05.2013)\n\nAngel Piaf (aka Chaynee) gets totally busted in today's FullyClothedPissing.com update when her husband Tom comes home early and catches her cheating through the window. Even though he's pissed off, the sight of his hot wife going at it only gets his dick hard, so he has no choice but to salvage his pride and go in and get a piece of Angel himself! This little slut of a cheater is always down for some clothes fetish fucking, so she gets right into it with her man and they go at it like the fashionable freaks\nthey are until the cuckold busts a nut all over exhausted Angel! Tom may now know that his wife is a deceitful, cheating slut, but after this fully clothed sex action he definitely gets the last laugh!\n\nScreens: &lt;a href=&quot;\nhttp://xxxhost.me/viewer.php?file=ybyhnt051kpob0jfr6mg.jpg&quot; rel=&quot;nofollow&quot; target=&quot;_NEW&quot;&gt;\nhttp://xxxhost.me/viewer.php?file=ybyhnt051kpob0jfr6mg.jpg&lt;/a&gt;\n &lt;a href=&quot;\nhttp://xxxhost.me/viewer.php?file=8oycd6mijveh6ccbkmbz.jpg&quot; rel=&quot;nofollow&quot; target=&quot;_NEW&quot;&gt;\nhttp://xxxhost.me/viewer.php?file=8oycd6mijveh6ccbkmbz.jpg&lt;/a&gt;","torrent":{"xt":"urn:btih:beedd86e08297e43af201a6e648ab4617e81b77a","amp;dn":"%5BFullyClothedSex%5D+Angel+Piaf+aka+Chaynee+%28The+Cuckold+Gets+The+L","amp;tr":["udp%3A%2F%2Ftracker.openbittorrent.com%3A80","udp%3A%2F%2Fopen.demonii.com%3A1337","udp%3A%2F%2Ftracker.coppersurfer.tk%3A6969","udp%3A%2F%2Fexodus.desync.com%3A6969"],"infoHash":"beedd86e08297e43af201a6e648ab4617e81b77a","infoHashBuffer":{"type":"Buffer","data":[190,237,216,110,8,41,126,67,175,32,26,110,100,138,180,97,126,129,183,122]},"announce":[],"urlList":[]}}