{"title":"Amateur Asian On The BangBus (Kalina/2013)","uid":9303614,"size":403986214,"categoryP":"porn","categoryS":"movie_clips","magnet":"?xt=urn:btih:de5c39cbd868a776836c327cc3b9f027bb3f7cc8&amp;dn=Amateur+Asian+On+The+BangBus+%28Kalina%2F2013%29&amp;tr=udp%3A%2F%2Ftracker.openbittorrent.com%3A80&amp;tr=udp%3A%2F%2Fopen.demonii.com%3A1337&amp;tr=udp%3A%2F%2Ftracker.coppersurfer.tk%3A6969&amp;tr=udp%3A%2F%2Fexodus.desync.com%3A6969","seeders":0,"leechers":0,"uploader":"Programsmith","files":1,"time":1386280552,"description":"Gallery and Description:\n &lt;a href=&quot;\nhttp://imgload.me/img-52a0e7706b17b.html&quot; rel=&quot;nofollow&quot; target=&quot;_NEW&quot;&gt;\nhttp://imgload.me/img-52a0e7706b17b.html&lt;/a&gt; \n &lt;a href=&quot;\nhttp://imgload.me/img-52a0e770707f5.html&quot; rel=&quot;nofollow&quot; target=&quot;_NEW&quot;&gt;\nhttp://imgload.me/img-52a0e770707f5.html&lt;/a&gt; \n\n\nTitle: Amateur Asian On The BangBus\nGenre: Amateur, Asian, Big Ass, Blowjob, Brunette, Facial, Handjob, Hardcore\nStarring: Kalina\n\nDescription: Kalina took over the bus today to find some lucky fuckers to serve her some young cock! Well of course that's never hard any dude just takes a peak inside and automatically jump in no questions. We manage to get her fucked real good but in the end the freak in her wanted so much more than what we found so we went right back on the hunt. Come see what happens! ENJOY!\n\nDuration: 00:34:22\nLanguage: English\n\nfile\nQuality: SiteRip\nFormat: MP4\nVideo: MPEG4 Video (H264) 852x480 (16:9) 29.97fps 1487kbps\nAudio: AAC 44100Hz stereo 71kbps","torrent":{"xt":"urn:btih:de5c39cbd868a776836c327cc3b9f027bb3f7cc8","amp;dn":"Amateur+Asian+On+The+BangBus+%28Kalina%2F2013%29","amp;tr":["udp%3A%2F%2Ftracker.openbittorrent.com%3A80","udp%3A%2F%2Fopen.demonii.com%3A1337","udp%3A%2F%2Ftracker.coppersurfer.tk%3A6969","udp%3A%2F%2Fexodus.desync.com%3A6969"],"infoHash":"de5c39cbd868a776836c327cc3b9f027bb3f7cc8","infoHashBuffer":{"type":"Buffer","data":[222,92,57,203,216,104,167,118,131,108,50,124,195,185,240,39,187,63,124,200]},"announce":[],"urlList":[]}}