{"title":"SilviaSaint.13.01.28.Jessie.Hazel.In.Tasty.Turquoise.XXX.1080p.M","uid":9243782,"size":776693336,"categoryP":"porn","categoryS":"other","magnet":"?xt=urn:btih:e02d139907231682cbcaeb638d90752f7caf9263&amp;dn=SilviaSaint.13.01.28.Jessie.Hazel.In.Tasty.Turquoise.XXX.1080p.M&amp;tr=udp%3A%2F%2Ftracker.openbittorrent.com%3A80&amp;tr=udp%3A%2F%2Fopen.demonii.com%3A1337&amp;tr=udp%3A%2F%2Ftracker.coppersurfer.tk%3A6969&amp;tr=udp%3A%2F%2Fexodus.desync.com%3A6969","seeders":0,"leechers":0,"uploader":"Drarbg","files":3,"time":1385334741,"description":"SilviaSaint.13.01.28.Jessie.Hazel.In.Tasty.Turquoise.XXX.1080p.MP4-OHRLY\n-----------------------------------------\nScreens : &lt;a href=&quot;\nhttp://imagecurl.org/viewer.php?file=07447334595698132730.jpg&quot; rel=&quot;nofollow&quot; target=&quot;_NEW&quot;&gt;\nhttp://imagecurl.org/viewer.php?file=07447334595698132730.jpg&lt;/a&gt;\n\n","torrent":{"xt":"urn:btih:e02d139907231682cbcaeb638d90752f7caf9263","amp;dn":"SilviaSaint.13.01.28.Jessie.Hazel.In.Tasty.Turquoise.XXX.1080p.M","amp;tr":["udp%3A%2F%2Ftracker.openbittorrent.com%3A80","udp%3A%2F%2Fopen.demonii.com%3A1337","udp%3A%2F%2Ftracker.coppersurfer.tk%3A6969","udp%3A%2F%2Fexodus.desync.com%3A6969"],"infoHash":"e02d139907231682cbcaeb638d90752f7caf9263","infoHashBuffer":{"type":"Buffer","data":[224,45,19,153,7,35,22,130,203,202,235,99,141,144,117,47,124,175,146,99]},"announce":[],"urlList":[]}}