{"title":"Snabba Cash, Livet Deluxe (2013)(dvd5)(Nl subs) RETAIL SAM TBS","uid":9388207,"size":4688052054,"categoryP":"video","categoryS":"movies_dvdr","magnet":"?xt=urn:btih:e0e2c652875f0ee517b427d88105b689dc52d634&amp;dn=Snabba+Cash%2C+Livet+Deluxe+%282013%29%28dvd5%29%28Nl+subs%29+RETAIL+SAM+TBS&amp;tr=udp%3A%2F%2Ftracker.openbittorrent.com%3A80&amp;tr=udp%3A%2F%2Fopen.demonii.com%3A1337&amp;tr=udp%3A%2F%2Ftracker.coppersurfer.tk%3A6969&amp;tr=udp%3A%2F%2Fexodus.desync.com%3A6969","seeders":0,"leechers":1,"uploader":"Sammynet","files":-1,"time":1387837046,"description":"Snabba Cash - Livet Deluxe (2013)\nAlternatieve titels: Easy Money III, Easy Money: Life Deluxe\n\nDutch\nJohan leeft nu in ballingschap en is meer dan ooit vastberaden om er achter te\nkomen wat er met zijn vermiste zus Camilla gebeurd is. Elk spoor leidt hem naar\nde georganiseerde misdaad in Stockholm, waar Jorge op het punt staat om zijn\nlaatste slag te slaan: het plegen van de grootste overval uit de Zweedse\ngeschiedenis. Tijdens de complexe voorbereidingen ontmoet hij Nadja, een vrouw\nuit zijn verleden.\n\nEnglish\nJohn now lives in exile and is more determined than ever to find out what happened\nto his missing sister Camilla. Each track leads him to organized crime in Stockholm,\nwhere Jorge is about to strike his final blow.\n\nPost Information\nSource............: RETAIL\nFormaat...........: DVD5\nVideo.............: PAL / 16:9\nAudio.............: Dolby Digital 5.1\nGenre.............: Crime / Drama / Thriller\nSubs..............: Dutch\nMenu..............: Yes\nPublication.Year..: 2013\nCover.&amp;.label.....: Yes\nAudio.............: Swedish\nRunningTime.......: 127 minutes\n &lt;a href=&quot;\nhttp://www.imdb.com/title/tt2427502/&quot; rel=&quot;nofollow&quot; target=&quot;_NEW&quot;&gt;\nhttp://www.imdb.com/title/tt2427502/&lt;/a&gt;\n &lt;a href=&quot;\nhttp://www.moviemeter.nl/film/92646&quot; rel=&quot;nofollow&quot; target=&quot;_NEW&quot;&gt;\nhttp://www.moviemeter.nl/film/92646&lt;/a&gt;\n\nSeeden wordt op prijs gesteld, om deze torrent in leven te houden.\n\nDon`t quit after you finished the download, but keep seeding.","torrent":{"xt":"urn:btih:e0e2c652875f0ee517b427d88105b689dc52d634","amp;dn":"Snabba+Cash%2C+Livet+Deluxe+%282013%29%28dvd5%29%28Nl+subs%29+RETAIL+SAM+TBS","amp;tr":["udp%3A%2F%2Ftracker.openbittorrent.com%3A80","udp%3A%2F%2Fopen.demonii.com%3A1337","udp%3A%2F%2Ftracker.coppersurfer.tk%3A6969","udp%3A%2F%2Fexodus.desync.com%3A6969"],"infoHash":"e0e2c652875f0ee517b427d88105b689dc52d634","infoHashBuffer":{"type":"Buffer","data":[224,226,198,82,135,95,14,229,23,180,39,216,129,5,182,137,220,82,214,52]},"announce":[],"urlList":[]}}