{"title":"Home Sweet Home (2013)(dvd5)(Nl subs) RETAIL SAM TBS","uid":9429387,"size":4635160152,"categoryP":"video","categoryS":"movies_dvdr","magnet":"?xt=urn:btih:e9191b4459aee037984f6a3a7c4fce90acc69444&amp;dn=Home+Sweet+Home+%282013%29%28dvd5%29%28Nl+subs%29+RETAIL+SAM+TBS&amp;tr=udp%3A%2F%2Ftracker.openbittorrent.com%3A80&amp;tr=udp%3A%2F%2Fopen.demonii.com%3A1337&amp;tr=udp%3A%2F%2Ftracker.coppersurfer.tk%3A6969&amp;tr=udp%3A%2F%2Fexodus.desync.com%3A6969","seeders":0,"leechers":1,"uploader":"Sammynet","files":-1,"time":1388763919,"description":"Home Sweet Home (2013)\n\nDutch\nHet pasgetrouwde stel Frank en Sara maken de ultieme nachtmerrie mee wanneer\nze net thuiskomen van een etentje en een ongenodigde gast aantreffen. Gevangen\ndoor deze methodische moordenaar in hun eigen huis, moet het stel er alles aan\ndoen om te ontsnappen aan zijn gestoorde spelletje.\n\nEnglish\nA young married couple comes home from a date night to discover that they are\nimprisoned in their own house with a methodical killer inside. \n\nPost Information\nSource............: RETAIL\nFormaat...........: DVD5\nVideo.............: PAL / 16:9\nAudio.............: Dolby Digital 5.1\nGenre.............: Horror / Thriller\nSubs..............: Dutch\nMenu..............: Yes\nPublication.Year..: 2013\nCover.&amp;.label.....: Yes\nAudio.............: Englisch\nRunningTime.......: 80 minutes\n &lt;a href=&quot;\nhttp://www.imdb.com/title/tt2348394/&quot; rel=&quot;nofollow&quot; target=&quot;_NEW&quot;&gt;\nhttp://www.imdb.com/title/tt2348394/&lt;/a&gt;\n &lt;a href=&quot;\nhttp://www.moviemeter.nl/film/93820&quot; rel=&quot;nofollow&quot; target=&quot;_NEW&quot;&gt;\nhttp://www.moviemeter.nl/film/93820&lt;/a&gt;\n\nSeeden wordt op prijs gesteld, om deze torrent in leven te houden.\n\nDon`t quit after you finished the download, but keep seeding.","torrent":{"xt":"urn:btih:e9191b4459aee037984f6a3a7c4fce90acc69444","amp;dn":"Home+Sweet+Home+%282013%29%28dvd5%29%28Nl+subs%29+RETAIL+SAM+TBS","amp;tr":["udp%3A%2F%2Ftracker.openbittorrent.com%3A80","udp%3A%2F%2Fopen.demonii.com%3A1337","udp%3A%2F%2Ftracker.coppersurfer.tk%3A6969","udp%3A%2F%2Fexodus.desync.com%3A6969"],"infoHash":"e9191b4459aee037984f6a3a7c4fce90acc69444","infoHashBuffer":{"type":"Buffer","data":[233,25,27,68,89,174,224,55,152,79,106,58,124,79,206,144,172,198,148,68]},"announce":[],"urlList":[]}}