{"title":"Easy.Rider.2.The.Ride.Back.2013.720p.BluRay.x264-EXQUiSiTE [Publ","uid":9279113,"size":3223543477,"categoryP":"video","categoryS":"hd___movies","magnet":"?xt=urn:btih:f4e8039bdc6e9ab41c48c503bba50cd3c36d84c8&amp;dn=Easy.Rider.2.The.Ride.Back.2013.720p.BluRay.x264-EXQUiSiTE+%5BPubl&amp;tr=udp%3A%2F%2Ftracker.openbittorrent.com%3A80&amp;tr=udp%3A%2F%2Fopen.demonii.com%3A1337&amp;tr=udp%3A%2F%2Ftracker.coppersurfer.tk%3A6969&amp;tr=udp%3A%2F%2Fexodus.desync.com%3A6969","seeders":0,"leechers":1,"uploader":"aoloffline","files":-1,"time":1385909164,"description":"\n                PublicHD - High-Definition Bittorrent Community\n      \n              ----------------------------------------------------\n\nEasy.Rider.2.The.Ride.Back.2013.720p.BluRay.x264-EXQUiSiTE [PublicHD]\n &lt;a href=&quot;\nhttp://www.imdb.com/title/tt1185838/&quot; rel=&quot;nofollow&quot; target=&quot;_NEW&quot;&gt;\nhttp://www.imdb.com/title/tt1185838/&lt;/a&gt;\n\nLength..............: 1h 38mn\nVideo...............: 1280x544 (X264 @ 23.976fps)\nBitrate.............: 4360Kbps\nAudio...............: DTS 1509 Kbps\nLanguage............: English\nSubtitles...........: N/A\nGenre ..............:  | Adventure\n\n\nS C R E E N S :\n &lt;a href=&quot;\nhttp://someimage.com/H5ca7ZR&quot; rel=&quot;nofollow&quot; target=&quot;_NEW&quot;&gt;\nhttp://someimage.com/H5ca7ZR&lt;/a&gt;\n &lt;a href=&quot;\nhttp://someimage.com/mZxiMCm&quot; rel=&quot;nofollow&quot; target=&quot;_NEW&quot;&gt;\nhttp://someimage.com/mZxiMCm&lt;/a&gt;\n &lt;a href=&quot;\nhttp://someimage.com/dxphXPA&quot; rel=&quot;nofollow&quot; target=&quot;_NEW&quot;&gt;\nhttp://someimage.com/dxphXPA&lt;/a&gt;\n &lt;a href=&quot;\nhttp://someimage.com/xbQCgyn&quot; rel=&quot;nofollow&quot; target=&quot;_NEW&quot;&gt;\nhttp://someimage.com/xbQCgyn&lt;/a&gt;\n &lt;a href=&quot;\nhttp://someimage.com/7ovH10e&quot; rel=&quot;nofollow&quot; target=&quot;_NEW&quot;&gt;\nhttp://someimage.com/7ovH10e&lt;/a&gt;\n\n\n","torrent":{"xt":"urn:btih:f4e8039bdc6e9ab41c48c503bba50cd3c36d84c8","amp;dn":"Easy.Rider.2.The.Ride.Back.2013.720p.BluRay.x264-EXQUiSiTE+%5BPubl","amp;tr":["udp%3A%2F%2Ftracker.openbittorrent.com%3A80","udp%3A%2F%2Fopen.demonii.com%3A1337","udp%3A%2F%2Ftracker.coppersurfer.tk%3A6969","udp%3A%2F%2Fexodus.desync.com%3A6969"],"infoHash":"f4e8039bdc6e9ab41c48c503bba50cd3c36d84c8","infoHashBuffer":{"type":"Buffer","data":[244,232,3,155,220,110,154,180,28,72,197,3,187,165,12,211,195,109,132,200]},"announce":[],"urlList":[]}}