{"title":"Screaming Assgasms.DVDRip.XxX","uid":9404760,"size":1632024093,"categoryP":"porn","categoryS":"movies","magnet":"?xt=urn:btih:f59a4972d527207c802826b6e379ab228ee08d45&amp;dn=Screaming+Assgasms.DVDRip.XxX&amp;tr=udp%3A%2F%2Ftracker.openbittorrent.com%3A80&amp;tr=udp%3A%2F%2Fopen.demonii.com%3A1337&amp;tr=udp%3A%2F%2Ftracker.coppersurfer.tk%3A6969&amp;tr=udp%3A%2F%2Fexodus.desync.com%3A6969","seeders":0,"leechers":0,"uploader":"handsome_hulk1253","files":5,"time":1388135918,"description":"Screenshots\n &lt;a href=&quot;\nhttp://adultxpictures.com/xxx/Jz9&quot; rel=&quot;nofollow&quot; target=&quot;_NEW&quot;&gt;\nhttp://adultxpictures.com/xxx/Jz9&lt;/a&gt; &lt;a href=&quot;\nhttp://adultxpictures.com/xxx/Jzv&quot; rel=&quot;nofollow&quot; target=&quot;_NEW&quot;&gt;\nhttp://adultxpictures.com/xxx/Jzv&lt;/a&gt; &lt;a href=&quot;\nhttp://adultxpictures.com/xxx/Jzy&quot; rel=&quot;nofollow&quot; target=&quot;_NEW&quot;&gt;\nhttp://adultxpictures.com/xxx/Jzy&lt;/a&gt; &lt;a href=&quot;\nhttp://adultxpictures.com/xxx/Jz3&quot; rel=&quot;nofollow&quot; target=&quot;_NEW&quot;&gt;\nhttp://adultxpictures.com/xxx/Jz3&lt;/a&gt; &lt;a href=&quot;\nhttp://adultxpictures.com/xxx/JzP&quot; rel=&quot;nofollow&quot; target=&quot;_NEW&quot;&gt;\nhttp://adultxpictures.com/xxx/JzP&lt;/a&gt; &lt;a href=&quot;\nhttp://adultxpictures.com/xxx/Jzj&quot; rel=&quot;nofollow&quot; target=&quot;_NEW&quot;&gt;\nhttp://adultxpictures.com/xxx/Jzj&lt;/a&gt;","torrent":{"xt":"urn:btih:f59a4972d527207c802826b6e379ab228ee08d45","amp;dn":"Screaming+Assgasms.DVDRip.XxX","amp;tr":["udp%3A%2F%2Ftracker.openbittorrent.com%3A80","udp%3A%2F%2Fopen.demonii.com%3A1337","udp%3A%2F%2Ftracker.coppersurfer.tk%3A6969","udp%3A%2F%2Fexodus.desync.com%3A6969"],"infoHash":"f59a4972d527207c802826b6e379ab228ee08d45","infoHashBuffer":{"type":"Buffer","data":[245,154,73,114,213,39,32,124,128,40,38,182,227,121,171,34,142,224,141,69]},"announce":[],"urlList":[]}}