{"title":"First suck then fuck and then&amp;hellip;","uid":9428207,"size":119342129,"categoryP":"porn","categoryS":"movie_clips","magnet":"?xt=urn:btih:fa0118731bb4e3ac69c893696b925cad6229f752&amp;dn=First+suck+then+fuck+and+then%26hellip%3B&amp;tr=udp%3A%2F%2Ftracker.openbittorrent.com%3A80&amp;tr=udp%3A%2F%2Fopen.demonii.com%3A1337&amp;tr=udp%3A%2F%2Ftracker.coppersurfer.tk%3A6969&amp;tr=udp%3A%2F%2Fexodus.desync.com%3A6969","seeders":0,"leechers":0,"uploader":"RaspotocjeGori","files":1,"time":1388747805,"description":" &lt;a href=&quot;http://fastfap.net/?p=2144&quot; rel=&quot;nofollow&quot; target=&quot;_NEW&quot;&gt;http://fastfap.net/?p=2144&lt;/a&gt;","torrent":{"xt":"urn:btih:fa0118731bb4e3ac69c893696b925cad6229f752","amp;dn":"First+suck+then+fuck+and+then%26hellip%3B","amp;tr":["udp%3A%2F%2Ftracker.openbittorrent.com%3A80","udp%3A%2F%2Fopen.demonii.com%3A1337","udp%3A%2F%2Ftracker.coppersurfer.tk%3A6969","udp%3A%2F%2Fexodus.desync.com%3A6969"],"infoHash":"fa0118731bb4e3ac69c893696b925cad6229f752","infoHashBuffer":{"type":"Buffer","data":[250,1,24,115,27,180,227,172,105,200,147,105,107,146,92,173,98,41,247,82]},"announce":[],"urlList":[]}}