{"title":"Babes - Dillion Harper - Teen Dream II / 06.Dec.13","uid":9305456,"size":965468206,"categoryP":"porn","categoryS":"hd___movies","magnet":"?xt=urn:btih:fc525e2542f4395a1b82abb240142e0f83ba9e6c&amp;dn=Babes+-+Dillion+Harper+-+Teen+Dream+II+%2F+06.Dec.13&amp;tr=udp%3A%2F%2Ftracker.openbittorrent.com%3A80&amp;tr=udp%3A%2F%2Fopen.demonii.com%3A1337&amp;tr=udp%3A%2F%2Ftracker.coppersurfer.tk%3A6969&amp;tr=udp%3A%2F%2Fexodus.desync.com%3A6969","seeders":0,"leechers":0,"uploader":"DavidL0ng","files":1,"time":1386310466,"description":"\nGenre: Side Fuck, Teen Role, Indoors, Small Ass\n\nDescription: Dillion Harper and her man Tyler could barely wait until they got home to collapse into a heap of passionate sexual energy. You can feel the passion between these two in every move and every moment they spend with skin touching skin. Tyler's desire is unmistakable as he flicks his tongue as gently as a butterfly's wings over Dillion's pussy. With every thrust of his eager prick into her pussy, Dillion moans with pleasure and begs him to push harder, deeper.\n\nDuration: 0:20:07\nType HD video: 1080p\nVideo Format: MP4\nVideo codec: H.264/AVC\nAudio codec: AAC\nVideo: MPEG4 Video (H264) 1920x1080 29.97fps 6000kbps\nAudio: AAC 48000Hz stereo 128kbps\n\nCover &amp; Screen : \n  &lt;a href=&quot;\nhttp://jollypix.net/?v=a69922e591.jpg&quot; rel=&quot;nofollow&quot; target=&quot;_NEW&quot;&gt;\nhttp://jollypix.net/?v=a69922e591.jpg&lt;/a&gt; &lt;a href=&quot;\nhttp://jollypix.net/?v=aa96325132.jpg&quot; rel=&quot;nofollow&quot; target=&quot;_NEW&quot;&gt;\nhttp://jollypix.net/?v=aa96325132.jpg&lt;/a&gt;\n\n\n===================================\n\nAll my Upload : \n   &lt;a href=&quot;\nhttps://thepiratebay.se/user/DavidL0ng/&quot; rel=&quot;nofollow&quot; target=&quot;_NEW&quot;&gt;\nhttps://thepiratebay.se/user/DavidL0ng/&lt;/a&gt;\n\n\nDOWNLOAD,ENJOY AND KEEP SEEDING !!!\n\n===================================\t","torrent":{"xt":"urn:btih:fc525e2542f4395a1b82abb240142e0f83ba9e6c","amp;dn":"Babes+-+Dillion+Harper+-+Teen+Dream+II+%2F+06.Dec.13","amp;tr":["udp%3A%2F%2Ftracker.openbittorrent.com%3A80","udp%3A%2F%2Fopen.demonii.com%3A1337","udp%3A%2F%2Ftracker.coppersurfer.tk%3A6969","udp%3A%2F%2Fexodus.desync.com%3A6969"],"infoHash":"fc525e2542f4395a1b82abb240142e0f83ba9e6c","infoHashBuffer":{"type":"Buffer","data":[252,82,94,37,66,244,57,90,27,130,171,178,64,20,46,15,131,186,158,108]},"announce":[],"urlList":[]}}